cyper.py
cyper-1.0.dist-info/LICENSE
cyper-1.0.dist-info/METADATA
cyper-1.0.dist-info/WHEEL
cyper-1.0.dist-info/top_level.txt
cyper-1.0.dist-info/RECORD
