Metadata-Version: 2.1
Name: cyper
Version: 1.0
Summary: Cython performed inline: compile and run your Cython snippets on the fly.
Home-page: https://github.com/syrte/cyper/
Author: Syrtis Major
Author-email: styr.py@gmail.com
License: MIT License
Keywords: cython
Platform: UNKNOWN
Classifier: Development Status :: 4 - Beta
Classifier: Topic :: Software Development :: Build Tools
Classifier: License :: OSI Approved :: MIT License
Classifier: Programming Language :: Python :: 2.7
Classifier: Programming Language :: Python :: 3
